LICENSE
README.md
setup.py
biodigest/__init__.py
biodigest/setup.py
biodigest/single_validation.py
biodigest/evaluation/__init__.py
biodigest/evaluation/background_models.py
biodigest/evaluation/comparator.py
biodigest/evaluation/config.py
biodigest/evaluation/score_calculator.py
biodigest/evaluation/d_utils/__init__.py
biodigest/evaluation/d_utils/eval_utils.py
biodigest/evaluation/d_utils/plotting_utils.py
biodigest/evaluation/d_utils/runner_utils.py
biodigest/evaluation/mappers/__init__.py
biodigest/evaluation/mappers/disease_getter.py
biodigest/evaluation/mappers/gene_getter.py
biodigest/evaluation/mappers/mapper.py
biodigest/evaluation/mappers/mapping_transformer.py
biodigest/evaluation/mappers/mapping_utils.py
biodigest_light.egg-info/PKG-INFO
biodigest_light.egg-info/SOURCES.txt
biodigest_light.egg-info/dependency_links.txt
biodigest_light.egg-info/requires.txt
biodigest_light.egg-info/top_level.txt