Metadata-Version: 2.1
Name: biodigest-light
Version: 0.0.3
Summary: In silico validation of Disease and Gene Sets, Clusterings or Subnetworks (DIGEST)
Home-page: http://pypi.python.org/pypi/biodigest/
Author: Klaudia Adamowicz
Author-email: klaudia.adamowicz@uni-hamburg.de
License: LICENSE
Platform: UNKNOWN
Classifier: Programming Language :: Python :: 3.7
Classifier: Programming Language :: Python :: 3.8
Classifier: Programming Language :: Python :: 3.9
Classifier: Intended Audience :: Science/Research
Requires-Python: >=3.7
License-File: LICENSE
